mlexpt/__init__.py
mlexpt/cli.py
mlexpt/experiment.py
mlexpt/modelrunio.py
mlexpt/data/__init__.py
mlexpt/data/adding_features.py
mlexpt/data/dataload.py
mlexpt/metrics/__init__.py
mlexpt/metrics/statistics.py
mlexpt/ml/__init__.py
mlexpt/ml/core.py
mlexpt/ml/models.py
mlexpt/ml/classifiers/__init__.py
mlexpt/ml/classifiers/linear.py
mlexpt/ml/encoders/__init__.py
mlexpt/ml/encoders/dictembedding.py
mlexpt/ml/encoders/sklearnencoders.py
mlexpt/utils/__init__.py
mlexpt/utils/caching.py
mlexpt/utils/core.py
mlexpt/utils/datatransform.py
mlexpt/utils/embeddings.py
ml_experiment-0.0.9.dist-info/LICENSE
ml_experiment-0.0.9.dist-info/METADATA
ml_experiment-0.0.9.dist-info/WHEEL
ml_experiment-0.0.9.dist-info/entry_points.txt
ml_experiment-0.0.9.dist-info/top_level.txt
ml_experiment-0.0.9.dist-info/RECORD
