Metadata-Version: 2.1
Name: ml-experiment
Version: 0.0.9
Summary: Machine Learning Experiment Framework
Author-email: Kwan Yuet Stephen Ho <stephenhky@yahoo.com.hk>
License: MIT
Project-URL: Repository, https://github.com/stephenhky/ml-experiment
Project-URL: Issues, https://github.com/stephenhky/ml-experiment/issues
Project-URL: Documentation, https://ml-experiment.readthedocs.io/
Keywords: machine learning,artificial intelligence
Classifier: Topic :: Scientific/Engineering :: Artificial Intelligence
Classifier: Topic :: Scientific/Engineering :: Mathematics
Classifier: Topic :: Software Development :: Libraries :: Python Modules
Classifier: Topic :: Software Development :: Version Control :: Git
Classifier: Programming Language :: Python :: 3.7
Classifier: Programming Language :: Python :: 3.8
Classifier: Programming Language :: Python :: 3.9
Classifier: Programming Language :: Python :: 3.10
Classifier: Programming Language :: Python :: 3.11
Classifier: Programming Language :: Python :: 3.12
Classifier: License :: OSI Approved :: MIT License
Classifier: Intended Audience :: Science/Research
Classifier: Intended Audience :: Developers
Requires-Python: >=3.7
License-File: LICENSE
Requires-Dist: numpy>=1.18.0
Requires-Dist: pandas>=1.0.0
Requires-Dist: torch>=1.5.0
Requires-Dist: tqdm>=4.46.0
Requires-Dist: scikit-learn>=0.23.0
Requires-Dist: scipy>=1.4.0
Requires-Dist: umap-learn>=0.4.4
Provides-Extra: test
Requires-Dist: unittest; extra == "test"
